zerohash/__init__.py
zerohash/api_requestor.py
zerohash/dummy.py
zerohash/error.py
zerohash/error_classes.py
zerohash/http_client.py
zerohash/object_classes.py
zerohash/resources/__init__.py
zerohash/resources/abstract/__init__.py
zerohash/resources/abstract/api_resource.py
zerohash/resources/abstract/createable.py
zerohash/resources/abstract/listable.py
zerohash/resources/accounts.py
zerohash/resources/digital_asset_addresses.py
zerohash/resources/error_object.py
zerohash/resources/index.py
zerohash/resources/liquidity_execute.py
zerohash/resources/liquidity_rfq.py
zerohash/resources/participants.py
zerohash/resources/participants_customers_new.py
zerohash/resources/time.py
zerohash/resources/trades.py
zerohash/resources/trades_batch.py
zerohash/resources/transfers.py
zerohash/resources/withdrawal.py
zerohash/resources/withdrawal_digital_asset_addresses.py
zerohash/resources/withdrawals.py
zerohash/util.py
zerohash/zerohash_object.py
zerohash/zerohash_response.py
zerohash_python-0.0.9.dist-info/WHEEL
zerohash_python-0.0.9.dist-info/METADATA
zerohash_python-0.0.9.dist-info/RECORD
